ikea_api/__init__.py
ikea_api/abc.py
ikea_api/base_ikea_api.py
ikea_api/constants.py
ikea_api/endpoints/__init__.py
ikea_api/endpoints/auth.py
ikea_api/endpoints/cart.py
ikea_api/endpoints/ingka_items.py
ikea_api/endpoints/order_capture.py
ikea_api/endpoints/pip_item.py
ikea_api/endpoints/purchases.py
ikea_api/endpoints/rotera_item.py
ikea_api/endpoints/search.py
ikea_api/endpoints/stock.py
ikea_api/error_handlers.py
ikea_api/exceptions.py
ikea_api/executors/__init__.py
ikea_api/executors/httpx.py
ikea_api/executors/requests.py
ikea_api/py.typed
ikea_api/utils.py
ikea_api/wrappers/__init__.py
ikea_api/wrappers/parsers/__init__.py
ikea_api/wrappers/parsers/ingka_items.py
ikea_api/wrappers/parsers/item_base.py
ikea_api/wrappers/parsers/order_capture.py
ikea_api/wrappers/parsers/pip_item.py
ikea_api/wrappers/parsers/purchases.py
ikea_api/wrappers/types.py
ikea_api/wrappers/wrappers.py
ikea_api-2.3.0.dist-info/LICENSE
ikea_api-2.3.0.dist-info/METADATA
ikea_api-2.3.0.dist-info/WHEEL
ikea_api-2.3.0.dist-info/RECORD
