Metadata-Version: 2.1
Name: ikea_api
Version: 2.3.0
Summary: Client for several IKEA's APIs
Home-page: https://github.com/vrslev/ikea-api-client
License: MIT
Keywords: ikea,ikea api,api,api client
Author: Lev Vereshchagin
Author-email: mail@vrslev.com
Requires-Python: >=3.8,<4.0
Classifier: Development Status :: 5 - Production/Stable
Classifier: License :: OSI Approved :: MIT License
Classifier: Natural Language :: English
Classifier: Programming Language :: Python :: 3
Classifier: Programming Language :: Python :: 3.8
Classifier: Programming Language :: Python :: 3.9
Classifier: Programming Language :: Python :: 3.10
Classifier: Programming Language :: Python :: 3.11
Classifier: Programming Language :: Python :: 3.12
Classifier: Programming Language :: Python :: Implementation :: CPython
Classifier: Typing :: Typed
Provides-Extra: all
Provides-Extra: httpx
Provides-Extra: requests
Provides-Extra: wrappers
Requires-Dist: httpx (>=0.23,<0.24) ; extra == "httpx" or extra == "all"
Requires-Dist: pydantic (>=2.0,<3.0) ; extra == "wrappers" or extra == "all"
Requires-Dist: requests ; extra == "requests" or extra == "all"
Requires-Dist: typing-extensions (>=4.0.0,<5.0.0) ; python_version < "3.10"
Project-URL: Repository, https://github.com/vrslev/ikea-api-client
